{"cameraMode":{"drawMode":24,"name":"Light Overlap","section":"Baked Global Illumination"},"sceneLighting":true,"audioPlay":false,"sceneViewState":{"m_AlwaysRefresh":false,"showFog":true,"showSkybox":true,"showFlares":true,"showImageEffects":true,"showParticleSystems":true,"showVisualEffectGraphs":true,"m_FxEnabled":false},"in2DMode":false,"pivot":{"x":4.050014972686768,"y":0.8569498062133789,"z":0.9503138065338135},"rotation":{"x":-0.2645704746246338,"y":0.35354989767074587,"z":-0.10497015714645386,"w":-0.8911200165748596},"size":6.239109039306641,"orthographic":true}